gway/__init__.py
gway/__main__.py
gway/console.py
gway/envs.py
gway/gateway.py
gway/logging.py
gway/runner.py
gway/sigils.py
gway/structs.py
gway-0.4.59.dist-info/licenses/LICENSE.md
gway-0.4.59.dist-info/METADATA
gway-0.4.59.dist-info/WHEEL
gway-0.4.59.dist-info/entry_points.txt
gway-0.4.59.dist-info/top_level.txt
gway-0.4.59.dist-info/RECORD
