Metadata-Version: 2.4
Name: gway
Version: 0.4.59
Summary: Software Project Infrastructure by https://www.gelectriic.com
Author-email: "Rafael J. Guillén-Osorio" <tecnologia@gelectriic.com>
License-Expression: MIT
Project-URL: Repository, https://github.com/arthexis/gway.git
Project-URL: Homepage, https://arthexis.com
Project-URL: Sponsor, https://www.gelectriic.com/
Classifier: Programming Language :: Python :: 3
Classifier: Operating System :: OS Independent
Requires-Python: >=3.10
License-File: LICENSE.md
Requires-Dist: toml
Requires-Dist: setuptools
Requires-Dist: twine
Requires-Dist: build
Requires-Dist: colorama
Requires-Dist: bottle
Requires-Dist: paste
Requires-Dist: requests
Requires-Dist: dateparser
Requires-Dist: fastapi
Requires-Dist: uvicorn
Requires-Dist: docutils
Requires-Dist: croniter
Requires-Dist: qrcode[pil]
Requires-Dist: cryptography
Requires-Dist: jinja2
Requires-Dist: pygame
Requires-Dist: python-multipart
Requires-Dist: httpx
Requires-Dist: websockets
Requires-Dist: pyperclip; platform_system == "Windows"
Requires-Dist: plyer
Requires-Dist: numpy
Requires-Dist: pygetwindow; platform_system == "Windows"
Requires-Dist: duckdb
Requires-Dist: pywin32; platform_system == "Windows"
Requires-Dist: selenium
Requires-Dist: webdriver-manager
Requires-Dist: bs4
Requires-Dist: markdown
Requires-Dist: pandas
Requires-Dist: openpyxl
Requires-Dist: coverage
Requires-Dist: argcomplete
Requires-Dist: PyJWT
Requires-Dist: sounddevice
Requires-Dist: PyYAML
Requires-Dist: pywebview
Provides-Extra: dev
Requires-Dist: pytest; extra == "dev"
Requires-Dist: pytest-cov; extra == "dev"
Dynamic: license-file
